[
  {
    "sn": "1",
    "commendDesc": "*[CommendThief_commendDesc_1]*"
  },
  {
    "sn": "2",
    "commendDesc": "*[CommendThief_commendDesc_2]*"
  },
  {
    "sn": "3",
    "commendDesc": "*[CommendThief_commendDesc_3]*"
  },
  {
    "sn": "4",
    "commendDesc": "*[CommendThief_commendDesc_4]*"
  },
  {
    "sn": "5",
    "commendDesc": "*[CommendThief_commendDesc_5]*"
  },
  {
    "sn": "6",
    "commendDesc": "*[CommendThief_commendDesc_6]*"
  },
  {
    "sn": "7",
    "commendDesc": "*[CommendThief_commendDesc_7]*"
  },
  {
    "sn": "8",
    "commendDesc": "*[CommendThief_commendDesc_8]*"
  },
  {
    "sn": "101",
    "commendDesc": "*[CommendThief_commendDesc_101]*"
  },
  {
    "sn": "102",
    "commendDesc": "*[CommendThief_commendDesc_102]*"
  },
  {
    "sn": "103",
    "commendDesc": "*[CommendThief_commendDesc_103]*"
  },
  {
    "sn": "104",
    "commendDesc": "*[CommendThief_commendDesc_104]*"
  },
  {
    "sn": "105",
    "commendDesc": "*[CommendThief_commendDesc_105]*"
  },
  {
    "sn": "106",
    "commendDesc": "*[CommendThief_commendDesc_106]*"
  },
  {
    "sn": "107",
    "commendDesc": "*[CommendThief_commendDesc_107]*"
  },
  {
    "sn": "108",
    "commendDesc": "*[CommendThief_commendDesc_108]*"
  },
  {
    "sn": "109",
    "commendDesc": "*[CommendThief_commendDesc_109]*"
  },
  {
    "sn": "110",
    "commendDesc": "*[CommendThief_commendDesc_110]*"
  },
  {
    "sn": "111",
    "commendDesc": "*[CommendThief_commendDesc_111]*"
  },
  {
    "sn": "112",
    "commendDesc": "*[CommendThief_commendDesc_112]*"
  },
  {
    "sn": "113",
    "commendDesc": "*[CommendThief_commendDesc_113]*"
  },
  {
    "sn": "114",
    "commendDesc": "*[CommendThief_commendDesc_114]*"
  },
  {
    "sn": "115",
    "commendDesc": "*[CommendThief_commendDesc_115]*"
  },
  {
    "sn": "116",
    "commendDesc": "*[CommendThief_commendDesc_116]*"
  },
  {
    "sn": "117",
    "commendDesc": "*[CommendThief_commendDesc_117]*"
  },
  {
    "sn": "118",
    "commendDesc": "*[CommendThief_commendDesc_118]*"
  },
  {
    "sn": "119",
    "commendDesc": "*[CommendThief_commendDesc_119]*"
  },
  {
    "sn": "120",
    "commendDesc": "*[CommendThief_commendDesc_120]*"
  },
  {
    "sn": "121",
    "commendDesc": "*[CommendThief_commendDesc_121]*"
  },
  {
    "sn": "122",
    "commendDesc": "*[CommendThief_commendDesc_122]*"
  },
  {
    "sn": "123",
    "commendDesc": "*[CommendThief_commendDesc_123]*"
  },
  {
    "sn": "124",
    "commendDesc": "*[CommendThief_commendDesc_124]*"
  },
  {
    "sn": "125",
    "commendDesc": "*[CommendThief_commendDesc_125]*"
  },
  {
    "sn": "126",
    "commendDesc": "*[CommendThief_commendDesc_126]*"
  },
  {
    "sn": "127",
    "commendDesc": "*[CommendThief_commendDesc_127]*"
  },
  {
    "sn": "128",
    "commendDesc": "*[CommendThief_commendDesc_128]*"
  },
  {
    "sn": "129",
    "commendDesc": "*[CommendThief_commendDesc_129]*"
  },
  {
    "sn": "130",
    "commendDesc": "*[CommendThief_commendDesc_130]*"
  },
  {
    "sn": "131",
    "commendDesc": "*[CommendThief_commendDesc_131]*"
  },
  {
    "sn": "132",
    "commendDesc": "*[CommendThief_commendDesc_132]*"
  },
  {
    "sn": "134",
    "commendDesc": "*[CommendThief_commendDesc_134]*"
  },
  {
    "sn": "135",
    "commendDesc": "*[CommendThief_commendDesc_135]*"
  },
  {
    "sn": "136",
    "commendDesc": "*[CommendThief_commendDesc_136]*"
  },
  {
    "sn": "137",
    "commendDesc": "*[CommendThief_commendDesc_137]*"
  }
]