[
  {
    "sn": "1",
    "desc": "*[MonopolyRank_desc_1]*"
  },
  {
    "sn": "2",
    "desc": "*[MonopolyRank_desc_2]*"
  },
  {
    "sn": "3",
    "desc": "*[MonopolyRank_desc_3]*"
  },
  {
    "sn": "4",
    "desc": "*[MonopolyRank_desc_4]*"
  },
  {
    "sn": "5",
    "desc": "*[MonopolyRank_desc_5]*"
  },
  {
    "sn": "6",
    "desc": "*[MonopolyRank_desc_6]*"
  },
  {
    "sn": "7",
    "desc": "*[MonopolyRank_desc_7]*"
  },
  {
    "sn": "8",
    "desc": "*[MonopolyRank_desc_8]*"
  },
  {
    "sn": "9",
    "desc": "*[MonopolyRank_desc_9]*"
  },
  {
    "sn": "10",
    "desc": "*[MonopolyRank_desc_10]*"
  },
  {
    "sn": "11",
    "desc": "*[MonopolyRank_desc_11]*"
  },
  {
    "sn": "12",
    "desc": "*[MonopolyRank_desc_12]*"
  },
  {
    "sn": "13",
    "desc": "*[MonopolyRank_desc_13]*"
  },
  {
    "sn": "14",
    "desc": "*[MonopolyRank_desc_14]*"
  },
  {
    "sn": "15",
    "desc": "*[MonopolyRank_desc_15]*"
  }
]