[
  {
    "sn": "1",
    "face_name": "Stare"
  },
  {
    "sn": "3",
    "face_name": "Let's Go"
  },
  {
    "sn": "4",
    "face_name": "Welcome"
  },
  {
    "sn": "5",
    "face_name": "Texting"
  },
  {
    "sn": "6",
    "face_name": "Angry"
  },
  {
    "sn": "7",
    "face_name": "Tease"
  },
  {
    "sn": "8",
    "face_name": "Puzzled"
  },
  {
    "sn": "10",
    "face_name": "Looking Sharp"
  },
  {
    "sn": "11",
    "face_name": "Eat Up"
  },
  {
    "sn": "12",
    "face_name": "Last Words?"
  },
  {
    "sn": "13",
    "face_name": "Happy"
  },
  {
    "sn": "14",
    "face_name": "Home Run"
  },
  {
    "sn": "15",
    "face_name": "Tea Time"
  },
  {
    "sn": "16",
    "face_name": "No Words"
  },
  {
    "sn": "20",
    "face_name": "OK"
  },
  {
    "sn": "21",
    "face_name": "Love You"
  },
  {
    "sn": "22",
    "face_name": "Transform"
  },
  {
    "sn": "23",
    "face_name": "Elegant Entrance"
  },
  {
    "sn": "24",
    "face_name": "Hungry"
  },
  {
    "sn": "25",
    "face_name": "Yummy"
  },
  {
    "sn": "26",
    "face_name": "Shocked"
  },
  {
    "sn": "27",
    "face_name": "Selfie"
  },
  {
    "sn": "28",
    "face_name": "For You"
  },
  {
    "sn": "29",
    "face_name": "Cooking"
  },
  {
    "sn": "30",
    "face_name": "Acceptable"
  },
  {
    "sn": "31",
    "face_name": "Bath Time"
  },
  {
    "sn": "32",
    "face_name": "I Got This"
  },
  {
    "sn": "33",
    "face_name": "Big Fan"
  },
  {
    "sn": "39",
    "face_name": "Dream Team"
  },
  {
    "sn": "40",
    "face_name": "This Way"
  },
  {
    "sn": "41",
    "face_name": "Get In"
  },
  {
    "sn": "42",
    "face_name": "Whoa"
  },
  {
    "sn": "43",
    "face_name": "What to Do"
  },
  {
    "sn": "44",
    "face_name": "Pet"
  },
  {
    "sn": "45",
    "face_name": "Great Job"
  },
  {
    "sn": "46",
    "face_name": "Blow a Kiss"
  },
  {
    "sn": "47",
    "face_name": "Pose"
  },
  {
    "sn": "48",
    "face_name": "Fist of Justice"
  },
  {
    "sn": "49",
    "face_name": "Game On"
  },
  {
    "sn": "50",
    "face_name": "My Name Is"
  },
  {
    "sn": "52",
    "face_name": "Take Your Meds"
  },
  {
    "sn": "53",
    "face_name": "Which One?"
  },
  {
    "sn": "54",
    "face_name": "Lucky"
  },
  {
    "sn": "55",
    "face_name": "Showtime"
  },
  {
    "sn": "56",
    "face_name": "High Five"
  },
  {
    "sn": "57",
    "face_name": "Cheers"
  },
  {
    "sn": "58",
    "face_name": "Squabble"
  },
  {
    "sn": "59",
    "face_name": "Chit Chat"
  },
  {
    "sn": "60",
    "face_name": "Classic!"
  },
  {
    "sn": "61",
    "face_name": "Under Control"
  },
  {
    "sn": "62",
    "face_name": "Teach Me"
  },
  {
    "sn": "63",
    "face_name": "Thank You"
  },
  {
    "sn": "65",
    "face_name": "Thumbs Up"
  },
  {
    "sn": "67",
    "face_name": "Strange Alert"
  },
  {
    "sn": "68",
    "face_name": "Calling Card"
  },
  {
    "sn": "69",
    "face_name": "Take Your Heart"
  },
  {
    "sn": "70",
    "face_name": "Surprise"
  },
  {
    "sn": "71",
    "face_name": "Take a Look"
  },
  {
    "sn": "72",
    "face_name": "Thou Art I"
  },
  {
    "sn": "101",
    "face_name": "Keep Going"
  },
  {
    "sn": "102",
    "face_name": "Special Treat"
  },
  {
    "sn": "104",
    "face_name": "Handshake"
  },
  {
    "sn": "105",
    "face_name": "Good Song"
  },
  {
    "sn": "106",
    "face_name": "Cheer On"
  },
  {
    "sn": "107",
    "face_name": "Caught"
  },
  {
    "sn": "108",
    "face_name": "Victory"
  },
  {
    "sn": "109",
    "face_name": "Work Out"
  },
  {
    "sn": "110",
    "face_name": "Sparkle"
  },
  {
    "sn": "111",
    "face_name": "Tired"
  },
  {
    "sn": "112",
    "face_name": "Flustered"
  },
  {
    "sn": "113",
    "face_name": "Teary-Eyed"
  },
  {
    "sn": "114",
    "face_name": "Whisper"
  },
  {
    "sn": "115",
    "face_name": "Excited"
  },
  {
    "sn": "116",
    "face_name": "Chow Down"
  },
  {
    "sn": "117",
    "face_name": "Overwhelmed"
  },
  {
    "sn": "118",
    "face_name": "Confused"
  },
  {
    "sn": "119",
    "face_name": "Panic"
  },
  {
    "sn": "120",
    "face_name": "Bleh!"
  },
  {
    "sn": "121",
    "face_name": "Giggle"
  },
  {
    "sn": "122",
    "face_name": "Shopping"
  },
  {
    "sn": "123",
    "face_name": "I'll Teach You"
  },
  {
    "sn": "125",
    "face_name": "Ohoho"
  },
  {
    "sn": "131",
    "face_name": "Focused"
  },
  {
    "sn": "132",
    "face_name": "Dismay"
  },
  {
    "sn": "133",
    "face_name": "Flowering"
  },
  {
    "sn": "135",
    "face_name": "Big Bucks"
  }
]