[
  {
    "sn": "41101",
    "checkpointNum": "Level 1",
    "title": "Beginner",
    "describe": "Enemy strength increases according to the level of the Phantom Thieves.",
    "victoryText": "AAAAAA==",
    "failText": "AAAAAA=="
  },
  {
    "sn": "41102",
    "checkpointNum": "Level 2",
    "title": "Intermediate",
    "describe": "Enemy strength increases according to the level of the Phantom Thieves.",
    "victoryText": "AAAAAA==",
    "failText": "AAAAAA=="
  },
  {
    "sn": "41103",
    "checkpointNum": "Level 3",
    "title": "Advanced",
    "describe": "Enemy strength increases according to the level of the Phantom Thieves.",
    "victoryText": "AAAAAA==",
    "failText": "AAAAAA=="
  },
  {
    "sn": "41104",
    "checkpointNum": "Level 4",
    "title": "Expert",
    "describe": "Enemy strength increases according to the level of the Phantom Thieves.",
    "victoryText": "AAAAAA==",
    "failText": "AAAAAA=="
  },
  {
    "sn": "41105",
    "checkpointNum": "Level 5",
    "title": "Master",
    "describe": "Enemy strength increases according to the level of the Phantom Thieves.",
    "victoryText": "AAAAAA==",
    "failText": "AAAAAA=="
  },
  {
    "sn": "41201",
    "checkpointNum": "Level 1",
    "title": "Beginner",
    "describe": "Enemy strength increases according to the level of the Phantom Thieves.",
    "victoryText": "AAAAAA==",
    "failText": "AAAAAA=="
  },
  {
    "sn": "41202",
    "checkpointNum": "Level 2",
    "title": "Intermediate",
    "describe": "Enemy strength increases according to the level of the Phantom Thieves.",
    "victoryText": "AAAAAA==",
    "failText": "AAAAAA=="
  },
  {
    "sn": "41203",
    "checkpointNum": "Level 3",
    "title": "Advanced",
    "describe": "Enemy strength increases according to the level of the Phantom Thieves.",
    "victoryText": "AAAAAA==",
    "failText": "AAAAAA=="
  },
  {
    "sn": "41204",
    "checkpointNum": "Level 4",
    "title": "Expert",
    "describe": "Enemy strength increases according to the level of the Phantom Thieves.",
    "victoryText": "AAAAAA==",
    "failText": "AAAAAA=="
  },
  {
    "sn": "41205",
    "checkpointNum": "Level 5",
    "title": "Master",
    "describe": "Enemy strength increases according to the level of the Phantom Thieves.",
    "victoryText": "AAAAAA==",
    "failText": "AAAAAA=="
  },
  {
    "sn": "41301",
    "checkpointNum": "Level 1",
    "title": "Beginner",
    "describe": "Enemy strength increases according to the level of the Phantom Thieves.",
    "victoryText": "AAAAAA==",
    "failText": "AAAAAA=="
  },
  {
    "sn": "41302",
    "checkpointNum": "Level 2",
    "title": "Intermediate",
    "describe": "Enemy strength increases according to the level of the Phantom Thieves.",
    "victoryText": "AAAAAA==",
    "failText": "AAAAAA=="
  },
  {
    "sn": "41303",
    "checkpointNum": "Level 3",
    "title": "Advanced",
    "describe": "Enemy strength increases according to the level of the Phantom Thieves.",
    "victoryText": "AAAAAA==",
    "failText": "AAAAAA=="
  },
  {
    "sn": "41304",
    "checkpointNum": "Level 4",
    "title": "Expert",
    "describe": "Enemy strength increases according to the level of the Phantom Thieves.",
    "victoryText": "AAAAAA==",
    "failText": "AAAAAA=="
  },
  {
    "sn": "41305",
    "checkpointNum": "Level 5",
    "title": "Master",
    "describe": "Enemy strength increases according to the level of the Phantom Thieves.",
    "victoryText": "AAAAAA==",
    "failText": "AAAAAA=="
  },
  {
    "sn": "41401",
    "checkpointNum": "Level 1",
    "title": "Beginner",
    "describe": "Enemy strength increases according to the level of the Phantom Thieves.",
    "victoryText": "AAAAAA==",
    "failText": "AAAAAA=="
  },
  {
    "sn": "41402",
    "checkpointNum": "Level 2",
    "title": "Intermediate",
    "describe": "Enemy strength increases according to the level of the Phantom Thieves.",
    "victoryText": "AAAAAA==",
    "failText": "AAAAAA=="
  },
  {
    "sn": "41403",
    "checkpointNum": "Level 3",
    "title": "Advanced",
    "describe": "Enemy strength increases according to the level of the Phantom Thieves.",
    "victoryText": "AAAAAA==",
    "failText": "AAAAAA=="
  },
  {
    "sn": "41404",
    "checkpointNum": "Level 4",
    "title": "Expert",
    "describe": "Enemy strength increases according to the level of the Phantom Thieves.",
    "victoryText": "AAAAAA==",
    "failText": "AAAAAA=="
  },
  {
    "sn": "41405",
    "checkpointNum": "Level 5",
    "title": "Master",
    "describe": "Enemy strength increases according to the level of the Phantom Thieves.",
    "victoryText": "AAAAAA==",
    "failText": "AAAAAA=="
  },
  {
    "sn": "42101",
    "checkpointNum": "Level 1",
    "title": "Physical and Gun Attacks 101",
    "describe": "Enemy strength increases according to the level of the Phantom Thieves.",
    "victoryText": "AAAAAA==",
    "failText": "AAAAAA=="
  },
  {
    "sn": "42102",
    "checkpointNum": "Level 2",
    "title": "Physical and Gun Attacks 101",
    "describe": "Enemy strength increases according to the level of the Phantom Thieves.",
    "victoryText": "AAAAAA==",
    "failText": "AAAAAA=="
  },
  {
    "sn": "42103",
    "checkpointNum": "Level 3",
    "title": "Physical and Gun Attacks 101",
    "describe": "Enemy strength increases according to the level of the Phantom Thieves.",
    "victoryText": "AAAAAA==",
    "failText": "AAAAAA=="
  },
  {
    "sn": "42104",
    "checkpointNum": "Level 4",
    "title": "Physical and Gun Attacks 101",
    "describe": "Enemy strength increases according to the level of the Phantom Thieves.",
    "victoryText": "AAAAAA==",
    "failText": "AAAAAA=="
  },
  {
    "sn": "42105",
    "checkpointNum": "Level 5",
    "title": "Physical and Gun Attacks 101",
    "describe": "Enemy strength increases according to the level of the Phantom Thieves.",
    "victoryText": "AAAAAA==",
    "failText": "AAAAAA=="
  },
  {
    "sn": "42201",
    "checkpointNum": "Level 1",
    "title": "Wind and Electricity 101",
    "describe": "Enemy strength increases according to the level of the Phantom Thieves.",
    "victoryText": "AAAAAA==",
    "failText": "AAAAAA=="
  },
  {
    "sn": "42202",
    "checkpointNum": "Level 2",
    "title": "Wind and Electricity 101",
    "describe": "Enemy strength increases according to the level of the Phantom Thieves.",
    "victoryText": "AAAAAA==",
    "failText": "AAAAAA=="
  },
  {
    "sn": "42203",
    "checkpointNum": "Level 3",
    "title": "Wind and Electricity 101",
    "describe": "Enemy strength increases according to the level of the Phantom Thieves.",
    "victoryText": "AAAAAA==",
    "failText": "AAAAAA=="
  },
  {
    "sn": "42204",
    "checkpointNum": "Level 4",
    "title": "Wind and Electricity 101",
    "describe": "Enemy strength increases according to the level of the Phantom Thieves.",
    "victoryText": "AAAAAA==",
    "failText": "AAAAAA=="
  },
  {
    "sn": "42205",
    "checkpointNum": "Level 5",
    "title": "Wind and Electricity 101",
    "describe": "Enemy strength increases according to the level of the Phantom Thieves.",
    "victoryText": "AAAAAA==",
    "failText": "AAAAAA=="
  },
  {
    "sn": "42301",
    "checkpointNum": "Level 1",
    "title": "Ice and Fire 101",
    "describe": "Enemy strength increases according to the level of the Phantom Thieves.",
    "victoryText": "AAAAAA==",
    "failText": "AAAAAA=="
  },
  {
    "sn": "42302",
    "checkpointNum": "Level 2",
    "title": "Ice and Fire 101",
    "describe": "Enemy strength increases according to the level of the Phantom Thieves.",
    "victoryText": "AAAAAA==",
    "failText": "AAAAAA=="
  },
  {
    "sn": "42303",
    "checkpointNum": "Level 3",
    "title": "Ice and Fire 101",
    "describe": "Enemy strength increases according to the level of the Phantom Thieves.",
    "victoryText": "AAAAAA==",
    "failText": "AAAAAA=="
  },
  {
    "sn": "42304",
    "checkpointNum": "Level 4",
    "title": "Ice and Fire 101",
    "describe": "Enemy strength increases according to the level of the Phantom Thieves.",
    "victoryText": "AAAAAA==",
    "failText": "AAAAAA=="
  },
  {
    "sn": "42305",
    "checkpointNum": "Level 5",
    "title": "Ice and Fire 101",
    "describe": "Enemy strength increases according to the level of the Phantom Thieves.",
    "victoryText": "AAAAAA==",
    "failText": "AAAAAA=="
  },
  {
    "sn": "42401",
    "checkpointNum": "Level 1",
    "title": "Nuclear and Psychokinesis 101",
    "describe": "Enemy strength increases according to the level of the Phantom Thieves.",
    "victoryText": "AAAAAA==",
    "failText": "AAAAAA=="
  },
  {
    "sn": "42402",
    "checkpointNum": "Level 2",
    "title": "Nuclear and Psychokinesis 101",
    "describe": "Enemy strength increases according to the level of the Phantom Thieves.",
    "victoryText": "AAAAAA==",
    "failText": "AAAAAA=="
  },
  {
    "sn": "42403",
    "checkpointNum": "Level 3",
    "title": "Nuclear and Psychokinesis 101",
    "describe": "Enemy strength increases according to the level of the Phantom Thieves.",
    "victoryText": "AAAAAA==",
    "failText": "AAAAAA=="
  },
  {
    "sn": "42404",
    "checkpointNum": "Level 4",
    "title": "Nuclear and Psychokinesis 101",
    "describe": "Enemy strength increases according to the level of the Phantom Thieves.",
    "victoryText": "AAAAAA==",
    "failText": "AAAAAA=="
  },
  {
    "sn": "42405",
    "checkpointNum": "Level 5",
    "title": "Nuclear and Psychokinesis 101",
    "describe": "Enemy strength increases according to the level of the Phantom Thieves.",
    "victoryText": "AAAAAA==",
    "failText": "AAAAAA=="
  },
  {
    "sn": "42501",
    "checkpointNum": "Level 1",
    "title": "Curse and Bless 101",
    "describe": "Enemy strength increases according to the level of the Phantom Thieves.",
    "victoryText": "AAAAAA==",
    "failText": "AAAAAA=="
  },
  {
    "sn": "42502",
    "checkpointNum": "Level 2",
    "title": "Curse and Bless 101",
    "describe": "Enemy strength increases according to the level of the Phantom Thieves.",
    "victoryText": "AAAAAA==",
    "failText": "AAAAAA=="
  },
  {
    "sn": "42503",
    "checkpointNum": "Level 3",
    "title": "Curse and Bless 101",
    "describe": "Enemy strength increases according to the level of the Phantom Thieves.",
    "victoryText": "AAAAAA==",
    "failText": "AAAAAA=="
  },
  {
    "sn": "42504",
    "checkpointNum": "Level 4",
    "title": "Curse and Bless 101",
    "describe": "Enemy strength increases according to the level of the Phantom Thieves.",
    "victoryText": "AAAAAA==",
    "failText": "AAAAAA=="
  },
  {
    "sn": "42505",
    "checkpointNum": "Level 5",
    "title": "Curse and Bless 101",
    "describe": "Enemy strength increases according to the level of the Phantom Thieves.",
    "victoryText": "AAAAAA==",
    "failText": "AAAAAA=="
  },
  {
    "sn": "43101",
    "checkpointNum": "Level 1",
    "title": "Body Tempering",
    "describe": "Enemy strength increases according to the level of the Phantom Thieves.",
    "victoryText": "AAAAAA==",
    "failText": "AAAAAA=="
  },
  {
    "sn": "43102",
    "checkpointNum": "Level 2",
    "title": "Body Tempering",
    "describe": "Enemy strength increases according to the level of the Phantom Thieves.",
    "victoryText": "AAAAAA==",
    "failText": "AAAAAA=="
  },
  {
    "sn": "43103",
    "checkpointNum": "Level 3",
    "title": "Body Tempering",
    "describe": "Enemy strength increases according to the level of the Phantom Thieves.",
    "victoryText": "AAAAAA==",
    "failText": "AAAAAA=="
  },
  {
    "sn": "43104",
    "checkpointNum": "Level 4",
    "title": "Body Tempering",
    "describe": "Enemy strength increases according to the level of the Phantom Thieves.",
    "victoryText": "AAAAAA==",
    "failText": "AAAAAA=="
  },
  {
    "sn": "43105",
    "checkpointNum": "Level 5",
    "title": "Body Tempering",
    "describe": "Enemy strength increases according to the level of the Phantom Thieves.",
    "victoryText": "AAAAAA==",
    "failText": "AAAAAA=="
  },
  {
    "sn": "43201",
    "checkpointNum": "Level 1",
    "title": "Zen Meditation",
    "describe": "Enemy strength increases according to the level of the Phantom Thieves.",
    "victoryText": "AAAAAA==",
    "failText": "AAAAAA=="
  },
  {
    "sn": "43202",
    "checkpointNum": "Level 2",
    "title": "Zen Meditation",
    "describe": "Enemy strength increases according to the level of the Phantom Thieves.",
    "victoryText": "AAAAAA==",
    "failText": "AAAAAA=="
  },
  {
    "sn": "43203",
    "checkpointNum": "Level 3",
    "title": "Zen Meditation",
    "describe": "Enemy strength increases according to the level of the Phantom Thieves.",
    "victoryText": "AAAAAA==",
    "failText": "AAAAAA=="
  },
  {
    "sn": "43204",
    "checkpointNum": "Level 4",
    "title": "Zen Meditation",
    "describe": "Enemy strength increases according to the level of the Phantom Thieves.",
    "victoryText": "AAAAAA==",
    "failText": "AAAAAA=="
  },
  {
    "sn": "43205",
    "checkpointNum": "Level 5",
    "title": "Zen Meditation",
    "describe": "Enemy strength increases according to the level of the Phantom Thieves.",
    "victoryText": "AAAAAA==",
    "failText": "AAAAAA=="
  },
  {
    "sn": "43301",
    "checkpointNum": "Level 1",
    "title": "Enlightenment",
    "describe": "Enemy strength increases according to the level of the Phantom Thieves.",
    "victoryText": "AAAAAA==",
    "failText": "AAAAAA=="
  },
  {
    "sn": "43302",
    "checkpointNum": "Level 2",
    "title": "Enlightenment",
    "describe": "Enemy strength increases according to the level of the Phantom Thieves.",
    "victoryText": "AAAAAA==",
    "failText": "AAAAAA=="
  },
  {
    "sn": "43303",
    "checkpointNum": "Level 3",
    "title": "Enlightenment",
    "describe": "Enemy strength increases according to the level of the Phantom Thieves.",
    "victoryText": "AAAAAA==",
    "failText": "AAAAAA=="
  },
  {
    "sn": "43304",
    "checkpointNum": "Level 4",
    "title": "Enlightenment",
    "describe": "Enemy strength increases according to the level of the Phantom Thieves.",
    "victoryText": "AAAAAA==",
    "failText": "AAAAAA=="
  },
  {
    "sn": "43305",
    "checkpointNum": "Level 5",
    "title": "Enlightenment",
    "describe": "Enemy strength increases according to the level of the Phantom Thieves.",
    "victoryText": "AAAAAA==",
    "failText": "AAAAAA=="
  },
  {
    "sn": "44101",
    "checkpointNum": "Level 1",
    "title": "Weapon Hunt Area A",
    "describe": "Enemy strength increases according to the level of the Phantom Thieves.",
    "victoryText": "AAAAAA==",
    "failText": "AAAAAA=="
  },
  {
    "sn": "44102",
    "checkpointNum": "Level 2",
    "title": "Weapon Hunt Area A",
    "describe": "Enemy strength increases according to the level of the Phantom Thieves.",
    "victoryText": "AAAAAA==",
    "failText": "AAAAAA=="
  },
  {
    "sn": "44103",
    "checkpointNum": "Level 3",
    "title": "Weapon Hunt Area A",
    "describe": "Enemy strength increases according to the level of the Phantom Thieves.",
    "victoryText": "AAAAAA==",
    "failText": "AAAAAA=="
  },
  {
    "sn": "44104",
    "checkpointNum": "Level 4",
    "title": "Weapon Hunt Area A",
    "describe": "Enemy strength increases according to the level of the Phantom Thieves.",
    "victoryText": "AAAAAA==",
    "failText": "AAAAAA=="
  },
  {
    "sn": "44105",
    "checkpointNum": "Level 5",
    "title": "Weapon Hunt Area A",
    "describe": "Enemy strength increases according to the level of the Phantom Thieves.",
    "victoryText": "AAAAAA==",
    "failText": "AAAAAA=="
  },
  {
    "sn": "44201",
    "checkpointNum": "Level 1",
    "title": "Weapon Hunt Area B",
    "describe": "Enemy strength increases according to the level of the Phantom Thieves.",
    "victoryText": "AAAAAA==",
    "failText": "AAAAAA=="
  },
  {
    "sn": "44202",
    "checkpointNum": "Level 2",
    "title": "Weapon Hunt Area B",
    "describe": "Enemy strength increases according to the level of the Phantom Thieves.",
    "victoryText": "AAAAAA==",
    "failText": "AAAAAA=="
  },
  {
    "sn": "44203",
    "checkpointNum": "Level 3",
    "title": "Weapon Hunt Area B",
    "describe": "Enemy strength increases according to the level of the Phantom Thieves.",
    "victoryText": "AAAAAA==",
    "failText": "AAAAAA=="
  },
  {
    "sn": "44204",
    "checkpointNum": "Level 4",
    "title": "Weapon Hunt Area B",
    "describe": "Enemy strength increases according to the level of the Phantom Thieves.",
    "victoryText": "AAAAAA==",
    "failText": "AAAAAA=="
  },
  {
    "sn": "44205",
    "checkpointNum": "Level 5",
    "title": "Weapon Hunt Area B",
    "describe": "Enemy strength increases according to the level of the Phantom Thieves.",
    "victoryText": "AAAAAA==",
    "failText": "AAAAAA=="
  },
  {
    "sn": "44301",
    "checkpointNum": "Level 1",
    "title": "Weapon Hunt Area C",
    "describe": "Enemy strength increases according to the level of the Phantom Thieves.",
    "victoryText": "AAAAAA==",
    "failText": "AAAAAA=="
  },
  {
    "sn": "44302",
    "checkpointNum": "Level 2",
    "title": "Weapon Hunt Area C",
    "describe": "Enemy strength increases according to the level of the Phantom Thieves.",
    "victoryText": "AAAAAA==",
    "failText": "AAAAAA=="
  },
  {
    "sn": "44303",
    "checkpointNum": "Level 3",
    "title": "Weapon Hunt Area C",
    "describe": "Enemy strength increases according to the level of the Phantom Thieves.",
    "victoryText": "AAAAAA==",
    "failText": "AAAAAA=="
  },
  {
    "sn": "44304",
    "checkpointNum": "Level 4",
    "title": "Weapon Hunt Area C",
    "describe": "Enemy strength increases according to the level of the Phantom Thieves.",
    "victoryText": "AAAAAA==",
    "failText": "AAAAAA=="
  },
  {
    "sn": "44305",
    "checkpointNum": "Level 5",
    "title": "Weapon Hunt Area C",
    "describe": "Enemy strength increases according to the level of the Phantom Thieves.",
    "victoryText": "AAAAAA==",
    "failText": "AAAAAA=="
  },
  {
    "sn": "100000",
    "checkpointNum": "Error: tnxotb-[Checkpoint_checkpointNum_100000]",
    "title": "Error: tnxotb-[Checkpoint_title_100000]",
    "describe": "Error: tnxotb-[Checkpoint_describe_100000]",
    "victoryText": "Open Chest",
    "failText": "Null"
  },
  {
    "sn": "100001",
    "checkpointNum": "Error: tnxotb-[Checkpoint_checkpointNum_100001]",
    "title": "Error: tnxotb-[Checkpoint_title_100001]",
    "describe": "Error: tnxotb-[Checkpoint_describe_100001]",
    "victoryText": "Open Chest",
    "failText": "Null"
  },
  {
    "sn": "100002",
    "checkpointNum": "Bonus Stage 1",
    "title": "Error: tnxotb-[Checkpoint_title_100002]",
    "describe": "Error: tnxotb-[Checkpoint_describe_100002]",
    "victoryText": "Open Chest",
    "failText": "Null"
  },
  {
    "sn": "100003",
    "checkpointNum": "Bonus Stage 2",
    "title": "Error: tnxotb-[Checkpoint_title_100003]",
    "describe": "Error: tnxotb-[Checkpoint_describe_100003]",
    "victoryText": "Open Chest",
    "failText": "Null"
  },
  {
    "sn": "100004",
    "checkpointNum": "Bonus Stage 3",
    "title": "Error: tnxotb-[Checkpoint_title_100004]",
    "describe": "Error: tnxotb-[Checkpoint_describe_100004]",
    "victoryText": "Open Chest",
    "failText": "Null"
  },
  {
    "sn": "100005",
    "checkpointNum": "Bonus Stage 4",
    "title": "Error: tnxotb-[Checkpoint_title_100005]",
    "describe": "Error: tnxotb-[Checkpoint_describe_100005]",
    "victoryText": "Open Chest",
    "failText": "Null"
  },
  {
    "sn": "100006",
    "checkpointNum": "Bonus Stage 5",
    "title": "Error: tnxotb-[Checkpoint_title_100006]",
    "describe": "Error: tnxotb-[Checkpoint_describe_100006]",
    "victoryText": "Open Chest",
    "failText": "Null"
  },
  {
    "sn": "100007",
    "checkpointNum": "Bonus Stage 6",
    "title": "Error: tnxotb-[Checkpoint_title_100007]",
    "describe": "Error: tnxotb-[Checkpoint_describe_100007]",
    "victoryText": "Open Chest",
    "failText": "Null"
  },
  {
    "sn": "100008",
    "checkpointNum": "Bonus Stage 7",
    "title": "Error: tnxotb-[Checkpoint_title_100008]",
    "describe": "Error: tnxotb-[Checkpoint_describe_100008]",
    "victoryText": "Open Chest",
    "failText": "Null"
  },
  {
    "sn": "100009",
    "checkpointNum": "Bonus Stage 8",
    "title": "Error: tnxotb-[Checkpoint_title_100009]",
    "describe": "Error: tnxotb-[Checkpoint_describe_100009]",
    "victoryText": "Open Chest",
    "failText": "Null"
  },
  {
    "sn": "100010",
    "checkpointNum": "Bonus Stage 9",
    "title": "Error: tnxotb-[Checkpoint_title_100010]",
    "describe": "Error: tnxotb-[Checkpoint_describe_100010]",
    "victoryText": "Open Chest",
    "failText": "Null"
  },
  {
    "sn": "100011",
    "checkpointNum": "Bonus Stage 10",
    "title": "Error: tnxotb-[Checkpoint_title_100011]",
    "describe": "Error: tnxotb-[Checkpoint_describe_100011]",
    "victoryText": "Open Chest",
    "failText": "Null"
  },
  {
    "sn": "100101",
    "checkpointNum": "Shinjuku Stalker",
    "title": "Error: tnxotb-[Checkpoint_title_100101]",
    "describe": "Change the heart of the Shinjuku Stalker Yoshito Seno",
    "victoryText": "Defeat Seno's Shadow",
    "failText": "Null"
  },
  {
    "sn": "300000",
    "checkpointNum": "Error: tnxotb-[Checkpoint_checkpointNum_300000]",
    "title": "Casino",
    "describe": "Explore the Palace and investigate the accusations",
    "victoryText": "AAAAAA==",
    "failText": "AAAAAA=="
  },
  {
    "sn": "1",
    "checkpointNum": "AAAAAA==",
    "title": "Error: tnxotb-[Checkpoint_title_1]",
    "describe": "Error: tnxotb-[Checkpoint_describe_1]",
    "victoryText": "AAAAAA==",
    "failText": "AAAAAA=="
  },
  {
    "sn": "49999",
    "checkpointNum": "AAAAAA==",
    "title": "Materials Dungeon",
    "describe": "Original Stage Open Slot",
    "victoryText": "AAAAAA==",
    "failText": "AAAAAA=="
  }
]