[
  {
    "sn": "101",
    "goalDesc": "Clear with no KO'd allies"
  },
  {
    "sn": "102",
    "goalDesc": "Clear within 20 actions"
  },
  {
    "sn": "103",
    "goalDesc": "Gain 25 or more ChocoPower"
  },
  {
    "sn": "201",
    "goalDesc": "Clear with no KO'd allies"
  },
  {
    "sn": "202",
    "goalDesc": "Clear within 20 actions"
  },
  {
    "sn": "203",
    "goalDesc": "Gain 50 or more ChocoPower"
  },
  {
    "sn": "301",
    "goalDesc": "Clear with no KO'd allies"
  },
  {
    "sn": "302",
    "goalDesc": "Clear within 20 actions"
  },
  {
    "sn": "303",
    "goalDesc": "Gain 25 or more ChocoPower"
  },
  {
    "sn": "401",
    "goalDesc": "Clear with no KO'd allies"
  },
  {
    "sn": "402",
    "goalDesc": "Gain 25 or more ChocoPower"
  },
  {
    "sn": "403",
    "goalDesc": "Gain 50 or more ChocoPower"
  },
  {
    "sn": "501",
    "goalDesc": "Clear with no KO'd allies"
  },
  {
    "sn": "502",
    "goalDesc": "Clear within 20 actions"
  },
  {
    "sn": "503",
    "goalDesc": "Gain 25 or more ChocoPower"
  },
  {
    "sn": "601",
    "goalDesc": "Clear with no KO'd allies"
  },
  {
    "sn": "602",
    "goalDesc": "Clear within 20 actions"
  },
  {
    "sn": "603",
    "goalDesc": "Gain 50 or more ChocoPower"
  }
]